gokyuzu/BlueskyEndpoints.py
gokyuzu/BlueskyHelper.py
gokyuzu/BlueskyRecords.py
gokyuzu/BlueskySession.py
gokyuzu/__init__.py
tests/__init__.py
tests/test_main.py
gokyuzu-2.0.7.dist-info/LICENSE
gokyuzu-2.0.7.dist-info/METADATA
gokyuzu-2.0.7.dist-info/WHEEL
gokyuzu-2.0.7.dist-info/top_level.txt
gokyuzu-2.0.7.dist-info/RECORD
